rdfc_proto/__init__.py
rdfc_proto/__init__.pyi
rdfc_proto/generated/common_pb2.py
rdfc_proto/generated/common_pb2.pyi
rdfc_proto/generated/common_pb2_grpc.py
rdfc_proto/generated/service_pb2.py
rdfc_proto/generated/service_pb2.pyi
rdfc_proto/generated/service_pb2_grpc.py
rdfc_proto-1.0.0.dist-info/METADATA
rdfc_proto-1.0.0.dist-info/WHEEL
rdfc_proto-1.0.0.dist-info/RECORD
