Metadata-Version: 2.4
Name: rdfc_proto
Version: 1.0.0
Summary: Python protobuf bindings for RDF-Connect
Project-URL: Homepage, https://rdf-connect.github.io
Project-URL: Repository, https://github.com/rdf-connect/proto
Project-URL: Issues, https://github.com/rdf-connect/proto/issues
Author-email: Ieben Smessaert <ieben.smessaert@ugent.be>
License-Expression: MIT
Requires-Python: >=3.12
Requires-Dist: grpcio-tools>=1.74.0
Requires-Dist: grpcio>=1.74.0
Requires-Dist: protobuf>=6.31.1
Requires-Dist: types-protobuf>=6.30.2.20250703
